osm2les_dev/__init__.py
osm2les_dev-1.0.3.dist-info/LICENSE
osm2les_dev-1.0.3.dist-info/METADATA
osm2les_dev-1.0.3.dist-info/WHEEL
osm2les_dev-1.0.3.dist-info/top_level.txt
osm2les_dev-1.0.3.dist-info/RECORD
