Metadata-Version: 2.1
Name: osm2les_dev
Version: 1.0.3
Summary: A package for processing and analyzing LES data with OSM.
Home-page: https://example.com/osm2les_dev
Author: Ranbir Grover
Author-email: ranbirgrover21@gmail.com
Classifier: Programming Language :: Python :: 3
Classifier: License :: OSI Approved :: MIT License
Classifier: Operating System :: OS Independent
Requires-Python: >=3.7
License-File: LICENSE
Requires-Dist: numpy
Requires-Dist: matplotlib
Requires-Dist: pandas
Requires-Dist: shapely
Requires-Dist: osmnx<=1.9.4
Requires-Dist: rioxarray
Requires-Dist: rasterio
Requires-Dist: geopy
Requires-Dist: geopandas
